Encryptionsuite/.main.py.kate-swp
Encryptionsuite/.master_ED.py.kate-swp
Encryptionsuite/__init__.py
Encryptionsuite/banner.py
Encryptionsuite/banner.py~
Encryptionsuite/bruteforce.py
Encryptionsuite/bruteforce.py~
Encryptionsuite/ciphers.py
Encryptionsuite/ciphers.py~
Encryptionsuite/ciphers_master.py
Encryptionsuite/colors.py
Encryptionsuite/colors.py~
Encryptionsuite/cypher.py
Encryptionsuite/dd.py
Encryptionsuite/dd.py~
Encryptionsuite/dd.py~~
Encryptionsuite/draft.py
Encryptionsuite/draft.py~
Encryptionsuite/enc_dec.py
Encryptionsuite/enc_dec_folder.py
Encryptionsuite/fedbanner.py
Encryptionsuite/main.py
Encryptionsuite/main.py~
Encryptionsuite/master_ED.py
Encryptionsuite/master_ED.py~
Encryptionsuite/master_enc_dec.py
Encryptionsuite/mciphers.py
Encryptionsuite/mores_cipher.py
Encryptionsuite/mores_cipher.py~
Encryptionsuite/pass_enc_dec.py
Encryptionsuite/ransom_decrypt.py
Encryptionsuite/ransom_payload.py
Encryptionsuite/ransom_server.py
Encryptionsuite/try.py
Encryptionsuite/try.py~
Encryptionsuite/__pycache__/__init__.cpython-311.pyc
Encryptionsuite/__pycache__/colors.cpython-311.pyc
Encryptionsuite/__pycache__/dd.cpython-311.pyc
Encryptionsuite/__pycache__/draft.cpython-311.pyc
Encryptionsuite/__pycache__/enc_dec.cpython-311.pyc
Encryptionsuite/__pycache__/enc_dec_folder.cpython-311.pyc
Encryptionsuite/__pycache__/fedbanner.cpython-311.pyc
Encryptionsuite/__pycache__/main.cpython-311.pyc
Encryptionsuite/__pycache__/master_ED.cpython-311.pyc
Encryptionsuite/__pycache__/master_enc_dec.cpython-311.pyc
Encryptionsuite/__pycache__/mciphers.cpython-311.pyc
Encryptionsuite/__pycache__/pass_enc_dec.cpython-311.pyc
Encryptionsuite/__pycache__/try.cpython-311.pyc
encryptionsuite-1.0.5.dist-info/LICENSE
encryptionsuite-1.0.5.dist-info/METADATA
encryptionsuite-1.0.5.dist-info/WHEEL
encryptionsuite-1.0.5.dist-info/entry_points.txt
encryptionsuite-1.0.5.dist-info/top_level.txt
encryptionsuite-1.0.5.dist-info/RECORD
