Metadata-Version: 2.1
Name: encryptionsuite
Version: 1.0.5
Author: Wambua aka skye-cyber
License: MIT
Keywords: Encryptionsuite,FED,File-encryptor,File-decryptor,encrypt-files,decrypt-files,encrypt,decrypt,cryptography
Classifier: Environment :: Console
Classifier: Natural Language :: English
Classifier: Operating System :: OS Independent
Classifier: Programming Language :: Python
Classifier: Programming Language :: Python :: 3 :: Only
Classifier: Programming Language :: Python :: 3
Classifier: Programming Language :: Python :: 3.7
Classifier: Programming Language :: Python :: 3.8
Classifier: Programming Language :: Python :: 3.9
Classifier: Programming Language :: Python :: 3.10
Classifier: Programming Language :: Python :: 3.11
Requires-Python: >=3.0
License-File: LICENSE
Requires-Dist: argparse
Requires-Dist: cryptography
